lygadgets/__init__.py
lygadgets/autolibrary.py
lygadgets/cell_translation.py
lygadgets/command_line.py
lygadgets/environment.py
lygadgets/gui_objects.py
lygadgets/markup.py
lygadgets/messaging.py
lygadgets/salt_linker.py
lygadgets/system_linker.py
lygadgets/technology.py
lygadgets-0.1.36.dist-info/LICENSE
lygadgets-0.1.36.dist-info/METADATA
lygadgets-0.1.36.dist-info/WHEEL
lygadgets-0.1.36.dist-info/entry_points.txt
lygadgets-0.1.36.dist-info/top_level.txt
lygadgets-0.1.36.dist-info/RECORD
