Metadata-Version: 2.1
Name: lygadgets
Version: 0.1.36
Summary: Tools to make klayout, the standalone, and python environments work better together
Home-page: https://github.com/atait/klayout-gadgets/
Author: Alex Tait
Author-email: alexander.tait@nist.gov
License: MIT
License-File: LICENSE
Requires-Dist: future
Requires-Dist: xmltodict
